peraq/mux_a.vhdl
library ieee;
use ieee.std_logic_1164.all;
use ieee.numeric_std.all;

entity mux_a is
    port (
        q_0, q_1, q_2, q_3 : in  std_logic_vector(7 downto 0);  -- saídas do regfile
        sel                 : in  std_logic_vector(7 downto 0);  -- op1 do IR
        reg_a_out           : out std_logic_vector(7 downto 0)   -- saída para ALU
    );
end entity;

architecture behavioral of mux_a is
begin
    -- Comportamento combinacional
    process(q_0, q_1, q_2, q_3, sel)
    begin
        case sel is
            when "00000000" => reg_a_out <= q_0;
            when "00000001" => reg_a_out <= q_1;
            when "00000010" => reg_a_out <= q_2;
            when "00000011" => reg_a_out <= q_3;
            when others => reg_a_out <= (others => '0');
        end case;
    end process;
end architecture;

peraq/regfile.vhdl
library ieee;
use ieee.std_logic_1164.all;
use ieee.numeric_std.all;

entity regfile is
    port (
        clk  : in std_logic;
        rst  : in std_logic;
        we   : in std_logic;
        addr : in unsigned(1 downto 0);
        data : in std_logic_vector(7 downto 0);
        q_0  : out std_logic_vector(7 downto 0);
        q_1  : out std_logic_vector(7 downto 0);
        q_2  : out std_logic_vector(7 downto 0);
        q_3  : out std_logic_vector(7 downto 0)
    );
end regfile;

architecture reg of regfile is
    type reg_array is array(0 to 3) of std_logic_vector(7 downto 0);
    signal regs : reg_array := (others => (others => '0'));
begin
    process(clk)
    begin
        -- CORREÇÃO: Mudado de falling_edge para RISING_EDGE
        if rising_edge(clk) then
            if rst = '1' then
                regs <= (others => (others => '0')); 
            elsif we = '1' then
                regs(to_integer(addr)) <= data;
            end if;
        end if;
    end process;

    q_0 <= regs(0);
    q_1 <= regs(1);
    q_2 <= regs(2);
    q_3 <= regs(3);
end reg;

peraq/control_unit.vhdl
library ieee;
use ieee.std_logic_1164.all;
use ieee.numeric_std.all;

entity control_unit is
    port (
        -- Entradas
        clk         : in  std_logic;
        reset       : in  std_logic;
        opcode_in   : in  std_logic_vector(7 downto 0);
        A           : in  std_logic_vector(7 downto 0);
        flags_in    : in  std_logic_vector(6 downto 0);
        
        -- Saídas de Controle (Datapath)
        pc_en       : out std_logic;
        ir_load_en  : out std_logic;
        rf_write_en : out std_logic;
        
        -- Controle da ALU
        alu_op      : out std_logic_vector(4 downto 0);
        alu_src_b_sel : out std_logic;
        
        -- Controle do Shifter
        shifter_ctrl_out  : out std_logic_vector(1 downto 0); 

        -- Controle do MUX de WriteBack
        reg_write_src_sel : out std_logic_vector(1 downto 0); 
        reg_write_addr : out std_logic_vector(1 downto 0);

        -- Saídas de Carga dos Flags
        ld_alu_flags_out  : out std_logic;
        ld_shf_flags_out  : out std_logic;
        
        -- Controle do Processador
        halt_out    : out std_logic -- indica que CU em estado halt
    );
end entity control_unit;

architecture fsm of control_unit is

    -- Cria tipo "estado"
    type state_type is (
        S_RESET, S_FETCH, S_DECODE, S_EXECUTE, S_WRITEBACK, S_HALT
    );

    signal state : state_type; -- sinal do estado

    -- Macros: opcode de shifter e nop
    constant OP_NOP     : std_logic_vector(7 downto 0) := x"00";
    constant OP_HALT    : std_logic_vector(7 downto 0) := x"01";
    constant OP_MOV_REG : std_logic_vector(7 downto 0) := x"10";
    constant OP_MOV_IMM : std_logic_vector(7 downto 0) := x"11";
    
    --Macros: opcode de ULA
    constant OP_ADD     : std_logic_vector(7 downto 0) := x"40";
    constant OP_SUB     : std_logic_vector(7 downto 0) := x"41";
    constant OP_AND     : std_logic_vector(7 downto 0) := x"42";
    constant OP_OR      : std_logic_vector(7 downto 0) := x"43";
    constant OP_XOR     : std_logic_vector(7 downto 0) := x"44";
    constant OP_NOT     : std_logic_vector(7 downto 0) := x"45";
    constant OP_CMP     : std_logic_vector(7 downto 0) := x"47";
    constant OP_NAND    : std_logic_vector(7 downto 0) := x"48";
    constant OP_NOR     : std_logic_vector(7 downto 0) := x"49";
    constant OP_XNOR    : std_logic_vector(7 downto 0) := x"4A";
    constant OP_PASS_B  : std_logic_vector(7 downto 0) := x"4B";
    
    constant OP_ADD_IMM : std_logic_vector(7 downto 0) := x"50";
    constant OP_SUB_IMM : std_logic_vector(7 downto 0) := x"51";
    constant OP_AND_IMM : std_logic_vector(7 downto 0) := x"62";
    constant OP_OR_IMM  : std_logic_vector(7 downto 0) := x"63";
    constant OP_XOR_IMM : std_logic_vector(7 downto 0) := x"64";

    constant OP_SHL     : std_logic_vector(7 downto 0) := x"70";
    constant OP_SHR     : std_logic_vector(7 downto 0) := x"71";
    constant OP_CMP_REG : std_logic_vector(7 downto 0) := x"78";
    constant OP_CMP_IMM : std_logic_vector(7 downto 0) := x"79";

    --Macros: operações da ula
    constant ALU_OP_ADD    : std_logic_vector(4 downto 0) := "00000";
    constant ALU_OP_SUB    : std_logic_vector(4 downto 0) := "00001";
    constant ALU_OP_CMP    : std_logic_vector(4 downto 0) := "00010";
    constant ALU_OP_AND    : std_logic_vector(4 downto 0) := "00110";
    constant ALU_OP_OR     : std_logic_vector(4 downto 0) := "00111";
    constant ALU_OP_XOR    : std_logic_vector(4 downto 0) := "01000";
    constant ALU_OP_NOT    : std_logic_vector(4 downto 0) := "01001";
    constant ALU_OP_NAND   : std_logic_vector(4 downto 0) := "01110";
    constant ALU_OP_NOR    : std_logic_vector(4 downto 0) := "01111";
    constant ALU_OP_XNOR   : std_logic_vector(4 downto 0) := "10000";
    constant ALU_OP_PASS_B : std_logic_vector(4 downto 0) := "10001";
    
begin
    
    process (clk, reset)
    begin
        if reset = '1' then --reset assíncrono, entra em estado de reset
            state <= S_RESET;
        
        elsif rising_edge(clk) then 
            case state is
                when S_RESET => --saí de reset para fetch (só se não estive reset = 1)
                    state <= S_FETCH;

                when S_FETCH => --direto para decode
                    state <= S_DECODE;

                when S_DECODE =>
                    if opcode_in = OP_HALT then -- vai p/ halt caso opcode de halt
                        state <= S_HALT;
                    else
                        state <= S_EXECUTE; --Execute em qualquer outro caso
                    end if;

                when S_EXECUTE =>
                    case opcode_in is --Opcodes que não precisam de writeback
                        when OP_CMP | OP_CMP_IMM | OP_CMP_REG |
                             OP_NOP | OP_HALT =>
                            state <= S_FETCH;

                        when others => -- Vai para WB em outros casos
                            state <= S_WRITEBACK;
                    end case;

                when S_WRITEBACK => --Direto para fetch
                    state <= S_FETCH;

                when S_HALT => --Continua em halt
                    state <= S_HALT;
            end case;
        end if;
    end process;

    process (state, opcode_in)
    begin

        case state is
            when S_FETCH => --pc e ir en para acrescentar + padrão dos sinais de exe e wb
                pc_en      <= '1';
                ir_load_en <= '1';

                rf_write_en   <= '0';
                alu_op        <= "00000"; 
                alu_src_b_sel <= '0';
                halt_out      <= '0'; 
                shifter_ctrl_out  <= "00";
                reg_write_src_sel <= "00";
                ld_alu_flags_out  <= '0';
                ld_shf_flags_out  <= '0';
                reg_write_addr <= "00";

            when S_DECODE => --volta para padrão os sinais de fetch
                pc_en      <= '0';
                ir_load_en <= '0';


            when S_EXECUTE =>
                case opcode_in is --Verifica se B imediato ou registrador (controla MUX)
                    when OP_MOV_IMM | OP_ADD_IMM | OP_SUB_IMM | 
                         OP_AND_IMM | OP_OR_IMM | OP_XOR_IMM | OP_CMP_IMM =>
                        alu_src_b_sel <= '1';
                    when others =>
                        alu_src_b_sel <= '0';
                end case;

                case opcode_in is --Operação a ser passada para ula TODO testar todas operações
                    when OP_ADD | OP_ADD_IMM => alu_op <= ALU_OP_ADD;
                    when OP_SUB | OP_SUB_IMM => alu_op <= ALU_OP_SUB;
                    when OP_AND | OP_AND_IMM => alu_op <= ALU_OP_AND;
                    when OP_OR  | OP_OR_IMM  => alu_op <= ALU_OP_OR;
                    when OP_XOR | OP_XOR_IMM => alu_op <= ALU_OP_XOR;
                    when OP_NOT             => alu_op <= ALU_OP_NOT;
                    when OP_NAND            => alu_op <= ALU_OP_NAND;
                    when OP_NOR             => alu_op <= ALU_OP_NOR;
                    when OP_XNOR            => alu_op <= ALU_OP_XNOR;
                    when OP_CMP | OP_CMP_REG | OP_CMP_IMM => alu_op <= ALU_OP_CMP; 
                    when OP_MOV_REG | OP_MOV_IMM | OP_PASS_B => alu_op <= ALU_OP_PASS_B;
                    when OP_SHL | OP_SHR    => alu_op <= "00000";
                    when others             => alu_op <= "00000";
                end case;

                case opcode_in is --Operação a ser passada para shifter
                    when OP_SHL => shifter_ctrl_out <= "01";
                    when OP_SHR => shifter_ctrl_out <= "10";
                    when others => shifter_ctrl_out <= "00";
                end case;

                case opcode_in is --Conrole de flag register (ALU ou SHIFTER)
                    when OP_ADD | OP_ADD_IMM | OP_SUB | OP_SUB_IMM |
                         OP_AND | OP_AND_IMM | OP_OR  | OP_OR_IMM  |
                         OP_XOR | OP_XOR_IMM | OP_NOT | OP_NAND |
                         OP_NOR | OP_XNOR |
                         OP_CMP | OP_CMP_REG | OP_CMP_IMM =>
                        ld_alu_flags_out <= '1'; --En flags alu

                    when OP_SHL | OP_SHR =>
                        ld_shf_flags_out <= '1'; --En flags shifter

                    when others =>
                        null;
                end case;

            when S_WRITEBACK =>
                rf_write_en <= '1'; --Permite escrita nos registradores

                case opcode_in is --Controla MUX de WB (saída vem da ALU: 00 ou SHIFTER: 01)
                    when OP_SHL | OP_SHR =>
                        reg_write_src_sel <= "01";
                        reg_write_addr <= A(1 downto 0);
                    
                    when OP_MOV_REG | OP_MOV_IMM | OP_PASS_B =>
                        reg_write_src_sel <= "00";
                        reg_write_addr <= A(1 downto 0);
                    when others =>
                        reg_write_src_sel <= "00";
                        reg_write_addr <= "11";
                end case;

            when S_HALT => --Sinal de HALT
                halt_out <= '1';

            when others =>
                REPORT "CU entrou em um estado desconhecido";
        end case;
    end process;

end architecture fsm;

peraq/tb_cu_registers_mux.vhdl
library ieee;
use ieee.std_logic_1164.all;
use ieee.numeric_std.all;

entity tb_cu_registers_mux is
end entity;

architecture behavioral of tb_cu_registers_mux is

    constant CLK_PERIOD : time := 10 ns;

    -- sinais de clock e reset
    signal clk_tb   : std_logic := '0';
    signal reset_tb : std_logic := '1';

    -- sinais da unidade de controle (usados apenas para compatibilidade)
    signal opcode_in_tb : std_logic_vector(7 downto 0) := (others => '0');
    signal A_tb         : std_logic_vector(7 downto 0) := (others => '0');
    signal flags_in_tb  : std_logic_vector(6 downto 0) := (others => '0');
    signal pc_en_tb, ir_load_en_tb, rf_write_en_tb, alu_src_b_sel_tb, halt_out_tb : std_logic;
    signal alu_op_tb : std_logic_vector(4 downto 0);
    signal shifter_ctrl_out_tb : std_logic_vector(1 downto 0);
    signal reg_write_src_sel_tb : std_logic_vector(1 downto 0);
    signal ld_alu_flags_out_tb, ld_shf_flags_out_tb : std_logic;

    -- sinais do regfile
    signal rf_we_tb    : std_logic := '0';
    signal rf_addr_tb  : unsigned(1 downto 0) := (others => '0');
    signal rf_data_tb  : std_logic_vector(7 downto 0) := (others => '0');
    signal q_0_tb, q_1_tb, q_2_tb, q_3_tb : std_logic_vector(7 downto 0);

    -- sinais do mux
    signal mux_sel_tb  : std_logic_vector(7 downto 0) := (others => '0');
    signal reg_a_out_tb: std_logic_vector(7 downto 0);

    -- função auxiliar para exibir std_logic_vector como string
    function to_string(slv : std_logic_vector) return string is
        variable result : string(1 to slv'length);
    begin
        for i in slv'range loop
            if slv(i) = '1' then
                result(i - slv'low + 1) := '1';
            elsif slv(i) = '0' then
                result(i - slv'low + 1) := '0';
            else
                result(i - slv'low + 1) := 'X';
            end if;
        end loop;
        return result;
    end function;

begin

    -------------------------------------------------------------------
    -- Instâncias dos módulos
    -------------------------------------------------------------------
    U_CU: entity work.control_unit
        port map (
            clk => clk_tb,
            reset => reset_tb,
            opcode_in => opcode_in_tb,
            A => A_tb,
            flags_in => flags_in_tb,
            pc_en => pc_en_tb,
            ir_load_en => ir_load_en_tb,
            rf_write_en => rf_write_en_tb,
            alu_op => alu_op_tb,
            alu_src_b_sel => alu_src_b_sel_tb,
            shifter_ctrl_out => shifter_ctrl_out_tb,
            reg_write_src_sel => reg_write_src_sel_tb,
            ld_alu_flags_out => ld_alu_flags_out_tb,
            ld_shf_flags_out => ld_shf_flags_out_tb,
            halt_out => halt_out_tb
        );

    U_RF: entity work.regfile
        port map (
            clk  => clk_tb,
            rst  => reset_tb,
            we   => rf_we_tb,
            addr => rf_addr_tb,
            data => rf_data_tb,
            q_0  => q_0_tb,
            q_1  => q_1_tb,
            q_2  => q_2_tb,
            q_3  => q_3_tb
        );

    U_MUX_A: entity work.mux_a
        port map (
            q_0 => q_0_tb,
            q_1 => q_1_tb,
            q_2 => q_2_tb,
            q_3 => q_3_tb,
            sel => mux_sel_tb,
            reg_a_out => reg_a_out_tb
        );

    -------------------------------------------------------------------
    -- Geração do clock
    -------------------------------------------------------------------
    clk_process : process
    begin
        while true loop
            clk_tb <= '0';
            wait for CLK_PERIOD / 2;
            clk_tb <= '1';
            wait for CLK_PERIOD / 2;
        end loop;
    end process;

    -------------------------------------------------------------------
    -- Estímulos
    -------------------------------------------------------------------
    stim_proc : process
    begin
        report "Iniciando simulação de escrita sequencial nos registradores..." severity note;

        -- reset
        reset_tb <= '1';
        wait for CLK_PERIOD * 2;
        reset_tb <= '0';
        report "Reset liberado." severity note;

        -------------------------------------------------------------------
        -- Escrita em cada registrador (regfile escreve em rising_edge)
        -------------------------------------------------------------------
        -- R0 = 0x88
        rf_addr_tb <= "00";
        rf_data_tb <= x"88";
        rf_we_tb   <= '1';
        wait until rising_edge(clk_tb);
        mux_sel_tb <= (others => '0'); -- seleciona R0
        report "Escrevendo em R0 valor: " & to_string(rf_data_tb) severity note;
        wait for 5 ns;
        report "MUX selecionou R0 -> Saída MUX: " & to_string(reg_a_out_tb) severity note;

        -- R1 = 0x44
        rf_addr_tb <= "01";
        rf_data_tb <= x"44";
        rf_we_tb   <= '1';
        wait until rising_edge(clk_tb);
        mux_sel_tb <= "00000001";
        report "Escrevendo em R1 valor: " & to_string(rf_data_tb) severity note;
        wait for 5 ns;
        report "MUX selecionou R1 -> Saída: " & to_string(reg_a_out_tb) severity note;

        -- R2 = 0xCC
        rf_addr_tb <= "10";
        rf_data_tb <= x"CC";
        rf_we_tb   <= '1';
        wait until rising_edge(clk_tb);
        mux_sel_tb <= "00000010";
        report "Escrevendo em R2 valor: " & to_string(rf_data_tb) severity note;
        wait for 5 ns;
        report "MUX selecionou R2 -> Saída: " & to_string(reg_a_out_tb) severity note;

        -- R3 = 0x22
        rf_addr_tb <= "11";
        rf_data_tb <= x"22";
        rf_we_tb   <= '1';
        wait until rising_edge(clk_tb);
        mux_sel_tb <= "00000011";
        report "Escrevendo em R3 valor: " & to_string(rf_data_tb) severity note;
        wait for 5 ns;
        report "MUX selecionou R3 -> Saída: " & to_string(reg_a_out_tb) severity note;

        rf_we_tb <= '0';
        report "Final da simulação." severity note;
        wait;
    end process;

end architecture;

peraq/tb_cu_registers_mux.vcd
$date
  Sat Nov 01 18:41:27 2025
$end
$version
  GHDL v0
$end
$timescale
  1 fs
$end
$scope module standard $end
$upscope $end
$scope module std_logic_1164 $end
$upscope $end
$scope module numeric_std $end
$upscope $end
$scope module tb_cu_registers_mux $end
$var reg 1 ! clk_tb $end
$var reg 1 " reset_tb $end
$var reg 8 # opcode_in_tb[7:0] $end
$var reg 8 $ a_tb[7:0] $end
$var reg 7 % flags_in_tb[6:0] $end
$var reg 1 & pc_en_tb $end
$var reg 1 ' ir_load_en_tb $end
$var reg 1 ( rf_write_en_tb $end
$var reg 1 ) alu_src_b_sel_tb $end
$var reg 1 * halt_out_tb $end
$var reg 5 + alu_op_tb[4:0] $end
$var reg 2 , shifter_ctrl_out_tb[1:0] $end
$var reg 2 - reg_write_src_sel_tb[1:0] $end
$var reg 1 . ld_alu_flags_out_tb $end
$var reg 1 / ld_shf_flags_out_tb $end
$var reg 1 0 rf_we_tb $end
$var reg 2 1 rf_addr_tb[1:0] $end
$var reg 8 2 rf_data_tb[7:0] $end
$var reg 8 3 q_0_tb[7:0] $end
$var reg 8 4 q_1_tb[7:0] $end
$var reg 8 5 q_2_tb[7:0] $end
$var reg 8 6 q_3_tb[7:0] $end
$var reg 8 7 mux_sel_tb[7:0] $end
$var reg 8 8 reg_a_out_tb[7:0] $end
$scope module u_cu $end
$var reg 1 9 clk $end
$var reg 1 : reset $end
$var reg 8 ; opcode_in[7:0] $end
$var reg 8 < a[7:0] $end
$var reg 7 = flags_in[6:0] $end
$var reg 1 > pc_en $end
$var reg 1 ? ir_load_en $end
$var reg 1 @ rf_write_en $end
$var reg 5 A alu_op[4:0] $end
$var reg 1 B alu_src_b_sel $end
$var reg 2 C shifter_ctrl_out[1:0] $end
$var reg 2 D reg_write_src_sel[1:0] $end
$var reg 2 E reg_write_addr[1:0] $end
$var reg 1 F ld_alu_flags_out $end
$var reg 1 G ld_shf_flags_out $end
$var reg 1 H halt_out $end
$comment state is not handled $end
$upscope $end
$scope module u_rf $end
$var reg 1 I clk $end
$var reg 1 J rst $end
$var reg 1 K we $end
$var reg 2 L addr[1:0] $end
$var reg 8 M data[7:0] $end
$var reg 8 N q_0[7:0] $end
$var reg 8 O q_1[7:0] $end
$var reg 8 P q_2[7:0] $end
$var reg 8 Q q_3[7:0] $end
$comment regs is not handled $end
$upscope $end
$scope module u_mux_a $end
$var reg 8 R q_0[7:0] $end
$var reg 8 S q_1[7:0] $end
$var reg 8 T q_2[7:0] $end
$var reg 8 U q_3[7:0] $end
$var reg 8 V sel[7:0] $end
$var reg 8 W reg_a_out[7:0] $end
$upscope $end
$upscope $end
$enddefinitions $end
#0
0!
1"
b00000000 #
b00000000 $
b0000000 %
U&
U'
U(
U)
U*
bUUUUU +
bUU ,
bUU -
U.
U/
00
b00 1
b00000000 2
b00000000 3
b00000000 4
b00000000 5
b00000000 6
b00000000 7
b00000000 8
09
1:
b00000000 ;
b00000000 <
b0000000 =
U>
U?
U@
bUUUUU A
UB
bUU C
bUU D
bUU E
UF
UG
UH
0I
1J
0K
b00 L
b00000000 M
b00000000 N
b00000000 O
b00000000 P
b00000000 Q
b00000000 R
b00000000 S
b00000000 T
b00000000 U
b00000000 V
b00000000 W
#5000000
1!
19
1I
#10000000
0!
09
0I
#15000000
1!
19
1I
#20000000
0!
0"
10
b10001000 2
09
0:
0I
0J
1K
b10001000 M
#25000000
1!
1&
1'
0(
0)
0*
b00000 +
b00 ,
b00 -
0.
0/
b10001000 3
b10001000 8
19
1>
1?
0@
b00000 A
0B
b00 C
b00 D
b00 E
0F
0G
0H
1I
b10001000 N
b10001000 R
b10001000 W
#30000000
0!
b01 1
b01000100 2
09
0I
b01 L
b01000100 M
#35000000
1!
0&
0'
b01000100 4
b00000001 7
b01000100 8
19
0>
0?
1I
b01000100 O
b01000100 S
b00000001 V
b01000100 W
#40000000
0!
b10 1
b11001100 2
09
0I
b10 L
b11001100 M
#45000000
1!
b11001100 5
b00000010 7
b11001100 8
19
1I
b11001100 P
b11001100 T
b00000010 V
b11001100 W
#50000000
0!
b11 1
b00100010 2
09
0I
b11 L
b00100010 M
#55000000
1!
1&
1'
b00100010 6
b00000011 7
b00100010 8
19
1>
1?
1I
b00100010 Q
b00100010 U
b00000011 V
b00100010 W
#60000000
0!
00
09
0I
0K
#65000000
1!
0&
0'
19
0>
0?
1I
#70000000
0!
09
0I
#75000000
1!
19
1I
#80000000
0!
09
0I
#85000000
1!
1&
1'
19
1>
1?
1I
#90000000
0!
09
0I
#95000000
1!
0&
0'
19
0>
0?
1I
#100000000
0!
09
0I
#105000000
1!
19
1I
#110000000
0!
09
0I
#115000000
1!
1&
1'
19
1>
1?
1I
#120000000
0!
09
0I
#125000000
1!
0&
0'
19
0>
0?
1I
#130000000
0!
09
0I
#135000000
1!
19
1I
#140000000
0!
09
0I
#145000000
1!
1&
1'
19
1>
1?
1I
#150000000
0!
09
0I
#155000000
1!
0&
0'
19
0>
0?
1I
#160000000
0!
09
0I
#165000000
1!
19
1I
#170000000
0!
09
0I
#175000000
1!
1&
1'
19
1>
1?
1I
#180000000
0!
09
0I
#185000000
1!
0&
0'
19
0>
0?
1I
